{"today":"20210215","queues":[{"taskName":"dailysignin","taskState":0,"willTime":"2021-02-15 08:14:09","waitTime":354},{"taskName":"winterTwo","taskState":0,"willTime":"2021-02-15 16:35:33","waitTime":508},{"taskName":"dxIntegralEveryDay","taskState":0,"willTime":"2021-02-15 10:44:14","waitTime":503},{"taskName":"dailygamebox","taskState":0,"willTime":"2021-02-15 08:18:29","waitTime":445},{"taskName":"dailylotteryintegral","taskState":0,"willTime":"2021-02-15 19:36:13","waitTime":58},{"taskName":"dailywoTree","taskState":0,"willTime":"2021-02-15 05:45:04","waitTime":520},{"taskName":"dailyBookRead","taskState":0,"willTime":"2021-02-15 05:38:53","waitTime":301},{"taskName":"dailyBookRead10doDraw","taskState":0,"willTime":"2021-02-15 19:48:57","waitTime":124},{"taskName":"dailyBookLuckdraw","taskState":0,"willTime":"2021-02-15 11:54:33","waitTime":125},{"taskName":"dailyLiuLan","taskState":0,"willTime":"2021-02-15 12:08:57","waitTime":18},{"taskName":"dailyGrabdollPage","taskState":0,"willTime":"2021-02-15 11:11:29","waitTime":551},{"taskName":"jflottery","taskState":0,"willTime":"2021-02-15 06:03:02","waitTime":251},{"taskName":"dailyYYY","taskState":0,"willTime":"2021-02-15 20:40:47","waitTime":387},{"taskName":"dailyVideoScratchcard","taskState":0,"willTime":"2021-02-15 11:24:21","waitTime":251},{"taskName":"dailyCheapStorePage","taskState":0,"willTime":"2021-02-15 00:00:00","waitTime":184},{"taskName":"dailyLKMH","taskState":0,"willTime":"2021-02-15 06:37:09","waitTime":343},{"taskName":"dailyYYQ","taskState":0,"willTime":"2021-02-15 15:24:51","waitTime":116},{"taskName":"dailyTurntablePage","taskState":0,"willTime":"2021-02-15 11:15:31","waitTime":311},{"taskName":"dailyVideo","taskState":0,"willTime":"2021-02-15 07:07:34","waitTime":582},{"taskName":"dailylottery","taskState":0,"willTime":"2021-02-15 10:10:56","waitTime":98},{"taskName":"producGameSignin","taskState":0,"willTime":"2021-02-15 04:03:14","waitTime":350},{"taskName":"dailygameflow","taskState":0,"willTime":"2021-02-15 14:17:44","waitTime":308},{"taskName":"dailygameIntegral","taskState":0,"willTime":"2021-02-15 05:49:25","waitTime":184},{"taskName":"dailyCourse","taskState":0,"willTime":"2021-02-15 09:00:00","waitTime":135},{"taskName":"dailycomment","taskState":0,"willTime":"2021-02-15 15:56:00","waitTime":258},{"taskName":"todayDailyTask","taskState":0,"willTime":"2021-02-15 20:00:00","waitTime":174},{"taskName":"gameYearBox","taskState":0,"willTime":"2021-02-15 20:00:00","waitTime":507},{"taskName":"NiujieSpikePrize","taskState":0,"willTime":"2021-02-15 09:36:00","waitTime":0},{"taskName":"NiujieTask","taskState":0,"willTime":"2021-02-15 12:45:05","waitTime":115},{"taskName":"NiujieReceiveCalf","taskState":0,"willTime":"2021-02-15 00:00:00","waitTime":576}]}
